bfield.py
bfield-0.9.1.dist-info/DESCRIPTION.rst
bfield-0.9.1.dist-info/METADATA
bfield-0.9.1.dist-info/RECORD
bfield-0.9.1.dist-info/WHEEL
bfield-0.9.1.dist-info/metadata.json
bfield-0.9.1.dist-info/top_level.txt
bfield-0.9.1.dist-info/zip-safe
