Metadata-Version: 2.0
Name: bfield
Version: 0.9.1
Summary: Convenient bit fields for int subclasses
Home-page: https://new.zygoon.pl/software/bfield/
Author: Zygmunt Krynicki
Author-email: me@zygoon.pl
License: MIT
Platform: any
Classifier: Development Status :: 4 - Beta
Classifier: Intended Audience :: Developers
Classifier: License :: OSI Approved :: MIT License
Classifier: Operating System :: POSIX
Classifier: Programming Language :: Python :: 2
Classifier: Programming Language :: Python :: 2.7
Classifier: Programming Language :: Python :: 3
Classifier: Programming Language :: Python :: 3.5
Classifier: Programming Language :: Python :: 3.6
Classifier: Topic :: Software Development
